sentinel2_downloader/__init__.py
sentinel2_downloader/sentinel.py
sentinel2_downloader-1.0.0.dist-info/METADATA
sentinel2_downloader-1.0.0.dist-info/WHEEL
sentinel2_downloader-1.0.0.dist-info/top_level.txt
sentinel2_downloader-1.0.0.dist-info/RECORD
