Metadata-Version: 2.1
Name: sentinel2-downloader
Version: 1.0.0
Summary: Utility for searching and downloading satellite images Dataspace Copernicus
Home-page: https://github.com/Azim-Kenzh/sentinel2_downloader
Author: Azimkozho Kenzhebek uulu
Author-email: azimkozho.inventor@gmail.com
Keywords: copernicus,sentinel,satellite,download,GIS
Classifier: License :: OSI Approved :: GNU General Public License v3 or later (GPLv3+)
Classifier: Programming Language :: Python :: 3
Classifier: Programming Language :: Python :: 3.8
Classifier: Programming Language :: Python :: 3.9
Classifier: Programming Language :: Python :: 3.10
Classifier: Programming Language :: Python :: 3.11
Classifier: Topic :: Scientific/Engineering :: GIS
Classifier: Topic :: Utilities
Requires-Dist: requests
Requires-Dist: tqdm
